state_interface/__init__.py
state_interface/io.py
state_interface/state.py
tests/__init__.py
tests/conftest.py
tests/test_read_state_input.py
state_interface-1.1.0.dist-info/METADATA
state_interface-1.1.0.dist-info/WHEEL
state_interface-1.1.0.dist-info/top_level.txt
state_interface-1.1.0.dist-info/RECORD
