Metadata-Version: 2.1
Name: state-interface
Version: 1.1.0
Summary: ASE STATE interface
Home-page: UNKNOWN
Author: Harry Handoko HALIM, Kurt Irvin Medina ROJAS, Ryo UEDA
Author-email: harry@cp.prec.eng.osaka-u.ac.jp, krojas@cp.prec.eng.osaka-u.ac.jp, u483198f@gmail.com
License: UNKNOWN
Platform: UNKNOWN
Classifier: Programming Language :: Python :: 3
Classifier: Programming Language :: Python :: 3.10
Requires-Dist: ase (==3.22.1)
